{"flowName":"save-text-in-buffer","model":{"key":"node1","type":"flowComponentInstance","props":{"componentName":"usr.atoms.inputs.TextField","componentInstance":"textField3","title":"textField3","searchName":"textField3","subtitle":"","inputs":[{"name":"props"}],"outputs":[{"name":"onChange","isSelected":true}]},"index":0,"children":[{"key":"node2","type":"flowUserFunction","props":{"functionName":"usr.logic.probe-api.saveBufferText","title":"saveBufferText","subtitle":"","searchName":"saveBufferText","inputs":[{"name":"callFunction","connectedTo":"onChange","isSelected":true}],"outputs":[{"name":"bufferText"}],"isSelected":true},"index":0}]}}